[
 {
  "defkey": "language",
  "defvalue": "en",
  "docstatus": 0,
  "doctype": "DefaultValue",
  "modified": "2024-07-10 09:28:32.502838",
  "name": "pkdlh6v6hv",
  "parent": "__default",
  "parentfield": "system_defaults",
  "parenttype": "__default"
 },
 {
  "defkey": "time_zone",
  "defvalue": "Asia/Kabul",
  "docstatus": 0,
  "doctype": "DefaultValue",
  "modified": "2024-07-10 09:28:32.653611",
  "name": "pkdnc8bf1s",
  "parent": "__default",
  "parentfield": "system_defaults",
  "parenttype": "__default"
 },
 {
  "defkey": "date_format",
  "defvalue": "dd-mm-yyyy",
  "docstatus": 0,
  "doctype": "DefaultValue",
  "modified": "2024-07-10 09:28:32.802938",
  "name": "pkdo4jp9hv",
  "parent": "__default",
  "parentfield": "system_defaults",
  "parenttype": "__default"
 },
 {
  "defkey": "float_precision",
  "defvalue": "3",
  "docstatus": 0,
  "doctype": "DefaultValue",
  "modified": "2024-07-10 09:28:32.947439",
  "name": "pkdqomo57t",
  "parent": "__default",
  "parentfield": "system_defaults",
  "parenttype": "__default"
 },
 {
  "defkey": "rounding_method",
  "defvalue": "Banker's Rounding",
  "docstatus": 0,
  "doctype": "DefaultValue",
  "modified": "2024-07-10 09:28:33.084008",
  "name": "pkdrm8url8",
  "parent": "__default",
  "parentfield": "system_defaults",
  "parenttype": "__default"
 },
 {
  "defkey": "enable_telemetry",
  "defvalue": "0",
  "docstatus": 0,
  "doctype": "DefaultValue",
  "modified": "2024-07-10 09:28:33.228298",
  "name": "pkdst856rv",
  "parent": "__default",
  "parentfield": "system_defaults",
  "parenttype": "__default"
 },
 {
  "defkey": "lang",
  "defvalue": "en",
  "docstatus": 0,
  "doctype": "DefaultValue",
  "modified": "2024-07-10 09:28:33.376468",
  "name": "pkdu0g0m00",
  "parent": "__default",
  "parentfield": "system_defaults",
  "parenttype": "__default"
 },
 {
  "defkey": "supp_master_name",
  "defvalue": "Supplier Name",
  "docstatus": 0,
  "doctype": "DefaultValue",
  "modified": "2024-07-10 09:28:38.663790",
  "name": "pkfjrnl3ki",
  "parent": "__default",
  "parentfield": "system_defaults",
  "parenttype": "__default"
 },
 {
  "defkey": "maintain_same_rate",
  "defvalue": "1",
  "docstatus": 0,
  "doctype": "DefaultValue",
  "modified": "2024-07-10 09:28:38.800205",
  "name": "pkfkced2sc",
  "parent": "__default",
  "parentfield": "system_defaults",
  "parenttype": "__default"
 },
 {
  "defkey": "buying_price_list",
  "defvalue": "Standard Buying",
  "docstatus": 0,
  "doctype": "DefaultValue",
  "modified": "2024-07-10 09:28:38.936782",
  "name": "pkfmajk16p",
  "parent": "__default",
  "parentfield": "system_defaults",
  "parenttype": "__default"
 },
 {
  "defkey": "cust_master_name",
  "defvalue": "Customer Name",
  "docstatus": 0,
  "doctype": "DefaultValue",
  "modified": "2024-07-10 09:28:39.329683",
  "name": "pkfpc75g9s",
  "parent": "__default",
  "parentfield": "system_defaults",
  "parenttype": "__default"
 },
 {
  "defkey": "maintain_same_sales_rate",
  "defvalue": "0",
  "docstatus": 0,
  "doctype": "DefaultValue",
  "modified": "2024-07-10 09:28:39.370703",
  "name": "pkfq2rlacv",
  "parent": "__default",
  "parentfield": "system_defaults",
  "parenttype": "__default"
 },
 {
  "defkey": "editable_price_list_rate",
  "defvalue": "0",
  "docstatus": 0,
  "doctype": "DefaultValue",
  "modified": "2024-07-10 09:28:39.512069",
  "name": "pkfrpbp87n",
  "parent": "__default",
  "parentfield": "system_defaults",
  "parenttype": "__default"
 },
 {
  "defkey": "selling_price_list",
  "defvalue": "Standard Selling",
  "docstatus": 0,
  "doctype": "DefaultValue",
  "modified": "2024-07-10 09:28:39.649413",
  "name": "pkfts3gqo2",
  "parent": "__default",
  "parentfield": "system_defaults",
  "parenttype": "__default"
 },
 {
  "defkey": "company",
  "defvalue": "RTe",
  "docstatus": 0,
  "doctype": "DefaultValue",
  "modified": "2024-07-10 09:28:40.180095",
  "name": "pkg1i5d2go",
  "parent": "__default",
  "parentfield": "system_defaults",
  "parenttype": "__default"
 },
 {
  "defkey": "currency",
  "defvalue": "AFN",
  "docstatus": 0,
  "doctype": "DefaultValue",
  "modified": "2024-07-10 09:28:40.222359",
  "name": "pkg2j7sd7h",
  "parent": "__default",
  "parentfield": "system_defaults",
  "parenttype": "__default"
 },
 {
  "defkey": "country",
  "defvalue": "Afghanistan",
  "docstatus": 0,
  "doctype": "DefaultValue",
  "modified": "2024-07-10 09:28:40.399376",
  "name": "pkg4b4kn06",
  "parent": "__default",
  "parentfield": "system_defaults",
  "parenttype": "__default"
 },
 {
  "defkey": "hide_currency_symbol",
  "defvalue": "",
  "docstatus": 0,
  "doctype": "DefaultValue",
  "modified": "2024-07-10 09:28:40.537173",
  "name": "pkg6sg857v",
  "parent": "__default",
  "parentfield": "system_defaults",
  "parenttype": "__default"
 },
 {
  "defkey": "disable_rounded_total",
  "defvalue": "0",
  "docstatus": 0,
  "doctype": "DefaultValue",
  "modified": "2024-07-10 09:28:40.675794",
  "name": "pkg79lmhki",
  "parent": "__default",
  "parentfield": "system_defaults",
  "parenttype": "__default"
 },
 {
  "defkey": "disable_in_words",
  "defvalue": "0",
  "docstatus": 0,
  "doctype": "DefaultValue",
  "modified": "2024-07-10 09:28:40.811958",
  "name": "pkg8vh8149",
  "parent": "__default",
  "parentfield": "system_defaults",
  "parenttype": "__default"
 },
 {
  "defkey": "item_naming_by",
  "defvalue": "Item Code",
  "docstatus": 0,
  "doctype": "DefaultValue",
  "modified": "2024-07-10 09:28:41.615911",
  "name": "pkggli494d",
  "parent": "__default",
  "parentfield": "system_defaults",
  "parenttype": "__default"
 },
 {
  "defkey": "stock_uom",
  "defvalue": "Nos",
  "docstatus": 0,
  "doctype": "DefaultValue",
  "modified": "2024-07-10 09:28:41.653679",
  "name": "pkghq1j4ih",
  "parent": "__default",
  "parentfield": "system_defaults",
  "parenttype": "__default"
 },
 {
  "defkey": "allow_negative_stock",
  "defvalue": "0",
  "docstatus": 0,
  "doctype": "DefaultValue",
  "modified": "2024-07-10 09:28:41.788721",
  "name": "pkgic67set",
  "parent": "__default",
  "parentfield": "system_defaults",
  "parenttype": "__default"
 },
 {
  "defkey": "default_warehouse",
  "defvalue": "Stores - R",
  "docstatus": 0,
  "doctype": "DefaultValue",
  "modified": "2024-07-10 09:28:41.925025",
  "name": "pkgj5nqsr4",
  "parent": "__default",
  "parentfield": "system_defaults",
  "parenttype": "__default"
 },
 {
  "defkey": "set_qty_in_transactions_based_on_serial_no_input",
  "defvalue": "1",
  "docstatus": 0,
  "doctype": "DefaultValue",
  "modified": "2024-07-10 09:28:42.060543",
  "name": "pkgl60ia9g",
  "parent": "__default",
  "parentfield": "system_defaults",
  "parenttype": "__default"
 },
 {
  "defkey": "use_serial_batch_fields",
  "defvalue": "1",
  "docstatus": 0,
  "doctype": "DefaultValue",
  "modified": "2024-07-10 09:28:42.198725",
  "name": "pkgmspq484",
  "parent": "__default",
  "parentfield": "system_defaults",
  "parenttype": "__default"
 },
 {
  "defkey": "desktop:home_page",
  "defvalue": "workspace",
  "docstatus": 0,
  "doctype": "DefaultValue",
  "modified": "2024-07-10 09:28:43.312909",
  "name": "pkh1ft3jj8",
  "parent": "__default",
  "parentfield": "system_defaults",
  "parenttype": "__default"
 },
 {
  "defkey": "app_name",
  "defvalue": "Frappe",
  "docstatus": 0,
  "doctype": "DefaultValue",
  "modified": "2024-07-10 10:24:35.751846",
  "name": "pi3l59lvff",
  "parent": "__default",
  "parentfield": "system_defaults",
  "parenttype": "__default"
 },
 {
  "defkey": "enable_onboarding",
  "defvalue": "0",
  "docstatus": 0,
  "doctype": "DefaultValue",
  "modified": "2024-07-10 10:24:35.753696",
  "name": "pi3lpmf6r4",
  "parent": "__default",
  "parentfield": "system_defaults",
  "parenttype": "__default"
 },
 {
  "defkey": "setup_complete",
  "defvalue": "0",
  "docstatus": 0,
  "doctype": "DefaultValue",
  "modified": "2024-07-10 10:24:35.754573",
  "name": "pi3liclea2",
  "parent": "__default",
  "parentfield": "system_defaults",
  "parenttype": "__default"
 },
 {
  "defkey": "disable_document_sharing",
  "defvalue": "0",
  "docstatus": 0,
  "doctype": "DefaultValue",
  "modified": "2024-07-10 10:24:35.755409",
  "name": "pi3l7e3tnt",
  "parent": "__default",
  "parentfield": "system_defaults",
  "parenttype": "__default"
 },
 {
  "defkey": "time_format",
  "defvalue": "HH:mm:ss",
  "docstatus": 0,
  "doctype": "DefaultValue",
  "modified": "2024-07-10 10:24:35.757025",
  "name": "pi3lp9p77q",
  "parent": "__default",
  "parentfield": "system_defaults",
  "parenttype": "__default"
 },
 {
  "defkey": "number_format",
  "defvalue": "#,###.##",
  "docstatus": 0,
  "doctype": "DefaultValue",
  "modified": "2024-07-10 10:24:35.757875",
  "name": "pi3leoush2",
  "parent": "__default",
  "parentfield": "system_defaults",
  "parenttype": "__default"
 },
 {
  "defkey": "first_day_of_the_week",
  "defvalue": "Sunday",
  "docstatus": 0,
  "doctype": "DefaultValue",
  "modified": "2024-07-10 10:24:35.758683",
  "name": "pi3l9rt9k0",
  "parent": "__default",
  "parentfield": "system_defaults",
  "parenttype": "__default"
 },
 {
  "defkey": "currency_precision",
  "defvalue": "",
  "docstatus": 0,
  "doctype": "DefaultValue",
  "modified": "2024-07-10 10:24:35.760421",
  "name": "pi3l88pbc1",
  "parent": "__default",
  "parentfield": "system_defaults",
  "parenttype": "__default"
 },
 {
  "defkey": "apply_strict_user_permissions",
  "defvalue": "0",
  "docstatus": 0,
  "doctype": "DefaultValue",
  "modified": "2024-07-10 10:24:35.762112",
  "name": "pi3ld0smk0",
  "parent": "__default",
  "parentfield": "system_defaults",
  "parenttype": "__default"
 },
 {
  "defkey": "allow_older_web_view_links",
  "defvalue": "0",
  "docstatus": 0,
  "doctype": "DefaultValue",
  "modified": "2024-07-10 10:24:35.763044",
  "name": "pi3lt51hpb",
  "parent": "__default",
  "parentfield": "system_defaults",
  "parenttype": "__default"
 },
 {
  "defkey": "session_expiry",
  "defvalue": "170:00",
  "docstatus": 0,
  "doctype": "DefaultValue",
  "modified": "2024-07-10 10:24:35.763892",
  "name": "pi3lue0hv0",
  "parent": "__default",
  "parentfield": "system_defaults",
  "parenttype": "__default"
 },
 {
  "defkey": "document_share_key_expiry",
  "defvalue": "30",
  "docstatus": 0,
  "doctype": "DefaultValue",
  "modified": "2024-07-10 10:24:35.764749",
  "name": "pi3lo2svmm",
  "parent": "__default",
  "parentfield": "system_defaults",
  "parenttype": "__default"
 },
 {
  "defkey": "deny_multiple_sessions",
  "defvalue": "0",
  "docstatus": 0,
  "doctype": "DefaultValue",
  "modified": "2024-07-10 10:24:35.765635",
  "name": "pi3loh5o7i",
  "parent": "__default",
  "parentfield": "system_defaults",
  "parenttype": "__default"
 },
 {
  "defkey": "disable_user_pass_login",
  "defvalue": "0",
  "docstatus": 0,
  "doctype": "DefaultValue",
  "modified": "2024-07-10 10:24:35.766563",
  "name": "pi3lu2d1ag",
  "parent": "__default",
  "parentfield": "system_defaults",
  "parenttype": "__default"
 },
 {
  "defkey": "allow_login_using_mobile_number",
  "defvalue": "0",
  "docstatus": 0,
  "doctype": "DefaultValue",
  "modified": "2024-07-10 10:24:35.767404",
  "name": "pi3l5fs3a2",
  "parent": "__default",
  "parentfield": "system_defaults",
  "parenttype": "__default"
 },
 {
  "defkey": "allow_login_using_user_name",
  "defvalue": "0",
  "docstatus": 0,
  "doctype": "DefaultValue",
  "modified": "2024-07-10 10:24:35.768241",
  "name": "pi3lf49agj",
  "parent": "__default",
  "parentfield": "system_defaults",
  "parenttype": "__default"
 },
 {
  "defkey": "login_with_email_link",
  "defvalue": "1",
  "docstatus": 0,
  "doctype": "DefaultValue",
  "modified": "2024-07-10 10:24:35.769077",
  "name": "pi3l682db3",
  "parent": "__default",
  "parentfield": "system_defaults",
  "parenttype": "__default"
 },
 {
  "defkey": "login_with_email_link_expiry",
  "defvalue": "10",
  "docstatus": 0,
  "doctype": "DefaultValue",
  "modified": "2024-07-10 10:24:35.769950",
  "name": "pi3lknhkd1",
  "parent": "__default",
  "parentfield": "system_defaults",
  "parenttype": "__default"
 },
 {
  "defkey": "allow_consecutive_login_attempts",
  "defvalue": "10",
  "docstatus": 0,
  "doctype": "DefaultValue",
  "modified": "2024-07-10 10:24:35.770998",
  "name": "pi3l4hielj",
  "parent": "__default",
  "parentfield": "system_defaults",
  "parenttype": "__default"
 },
 {
  "defkey": "allow_login_after_fail",
  "defvalue": "60",
  "docstatus": 0,
  "doctype": "DefaultValue",
  "modified": "2024-07-10 10:24:35.771835",
  "name": "pi3lkkmb4r",
  "parent": "__default",
  "parentfield": "system_defaults",
  "parenttype": "__default"
 },
 {
  "defkey": "enable_two_factor_auth",
  "defvalue": "0",
  "docstatus": 0,
  "doctype": "DefaultValue",
  "modified": "2024-07-10 10:24:35.772685",
  "name": "pi3le3o8t2",
  "parent": "__default",
  "parentfield": "system_defaults",
  "parenttype": "__default"
 },
 {
  "defkey": "bypass_2fa_for_retricted_ip_users",
  "defvalue": "0",
  "docstatus": 0,
  "doctype": "DefaultValue",
  "modified": "2024-07-10 10:24:35.773536",
  "name": "pi3l9s6li6",
  "parent": "__default",
  "parentfield": "system_defaults",
  "parenttype": "__default"
 },
 {
  "defkey": "bypass_restrict_ip_check_if_2fa_enabled",
  "defvalue": "0",
  "docstatus": 0,
  "doctype": "DefaultValue",
  "modified": "2024-07-10 10:24:35.774397",
  "name": "pi3leo9b9v",
  "parent": "__default",
  "parentfield": "system_defaults",
  "parenttype": "__default"
 },
 {
  "defkey": "two_factor_method",
  "defvalue": "OTP App",
  "docstatus": 0,
  "doctype": "DefaultValue",
  "modified": "2024-07-10 10:24:35.775210",
  "name": "pi3l1h0r2k",
  "parent": "__default",
  "parentfield": "system_defaults",
  "parenttype": "__default"
 },
 {
  "defkey": "otp_issuer_name",
  "defvalue": "Frappe Framework",
  "docstatus": 0,
  "doctype": "DefaultValue",
  "modified": "2024-07-10 10:24:35.776269",
  "name": "pi3lec4lur",
  "parent": "__default",
  "parentfield": "system_defaults",
  "parenttype": "__default"
 },
 {
  "defkey": "logout_on_password_reset",
  "defvalue": "1",
  "docstatus": 0,
  "doctype": "DefaultValue",
  "modified": "2024-07-10 10:24:35.777098",
  "name": "pi3lfhlu1c",
  "parent": "__default",
  "parentfield": "system_defaults",
  "parenttype": "__default"
 },
 {
  "defkey": "reset_password_link_expiry_duration",
  "defvalue": "1200",
  "docstatus": 0,
  "doctype": "DefaultValue",
  "modified": "2024-07-10 10:24:35.778176",
  "name": "pi3lodaqfm",
  "parent": "__default",
  "parentfield": "system_defaults",
  "parenttype": "__default"
 },
 {
  "defkey": "password_reset_limit",
  "defvalue": "3",
  "docstatus": 0,
  "doctype": "DefaultValue",
  "modified": "2024-07-10 10:24:35.779007",
  "name": "pi3lv2n1cd",
  "parent": "__default",
  "parentfield": "system_defaults",
  "parenttype": "__default"
 },
 {
  "defkey": "enable_password_policy",
  "defvalue": "1",
  "docstatus": 0,
  "doctype": "DefaultValue",
  "modified": "2024-07-10 10:24:35.779807",
  "name": "pi3ldg87fe",
  "parent": "__default",
  "parentfield": "system_defaults",
  "parenttype": "__default"
 },
 {
  "defkey": "minimum_password_score",
  "defvalue": "2",
  "docstatus": 0,
  "doctype": "DefaultValue",
  "modified": "2024-07-10 10:24:35.780661",
  "name": "pi3l0pck0s",
  "parent": "__default",
  "parentfield": "system_defaults",
  "parenttype": "__default"
 },
 {
  "defkey": "email_retry_limit",
  "defvalue": "3",
  "docstatus": 0,
  "doctype": "DefaultValue",
  "modified": "2024-07-10 10:24:35.781929",
  "name": "pi3li1fhm2",
  "parent": "__default",
  "parentfield": "system_defaults",
  "parenttype": "__default"
 },
 {
  "defkey": "disable_standard_email_footer",
  "defvalue": "0",
  "docstatus": 0,
  "doctype": "DefaultValue",
  "modified": "2024-07-10 10:24:35.782886",
  "name": "pi3l3lfh79",
  "parent": "__default",
  "parentfield": "system_defaults",
  "parenttype": "__default"
 },
 {
  "defkey": "hide_footer_in_auto_email_reports",
  "defvalue": "0",
  "docstatus": 0,
  "doctype": "DefaultValue",
  "modified": "2024-07-10 10:24:35.783765",
  "name": "pi3l5q0eh8",
  "parent": "__default",
  "parentfield": "system_defaults",
  "parenttype": "__default"
 },
 {
  "defkey": "attach_view_link",
  "defvalue": "1",
  "docstatus": 0,
  "doctype": "DefaultValue",
  "modified": "2024-07-10 10:24:35.784640",
  "name": "pi3l4nvh4j",
  "parent": "__default",
  "parentfield": "system_defaults",
  "parenttype": "__default"
 },
 {
  "defkey": "store_attached_pdf_document",
  "defvalue": "1",
  "docstatus": 0,
  "doctype": "DefaultValue",
  "modified": "2024-07-10 10:24:35.785490",
  "name": "pi3l8eol80",
  "parent": "__default",
  "parentfield": "system_defaults",
  "parenttype": "__default"
 },
 {
  "defkey": "allow_guests_to_upload_files",
  "defvalue": "0",
  "docstatus": 0,
  "doctype": "DefaultValue",
  "modified": "2024-07-10 10:24:35.787134",
  "name": "pi3lfqgn9j",
  "parent": "__default",
  "parentfield": "system_defaults",
  "parenttype": "__default"
 },
 {
  "defkey": "force_web_capture_mode_for_uploads",
  "defvalue": "0",
  "docstatus": 0,
  "doctype": "DefaultValue",
  "modified": "2024-07-10 10:24:35.787975",
  "name": "pi3lctqvnt",
  "parent": "__default",
  "parentfield": "system_defaults",
  "parenttype": "__default"
 },
 {
  "defkey": "strip_exif_metadata_from_uploaded_images",
  "defvalue": "1",
  "docstatus": 0,
  "doctype": "DefaultValue",
  "modified": "2024-07-10 10:24:35.788807",
  "name": "pi3ls1ngd1",
  "parent": "__default",
  "parentfield": "system_defaults",
  "parenttype": "__default"
 },
 {
  "defkey": "disable_system_update_notification",
  "defvalue": "0",
  "docstatus": 0,
  "doctype": "DefaultValue",
  "modified": "2024-07-10 10:24:35.789912",
  "name": "pi3lotakaa",
  "parent": "__default",
  "parentfield": "system_defaults",
  "parenttype": "__default"
 },
 {
  "defkey": "disable_change_log_notification",
  "defvalue": "0",
  "docstatus": 0,
  "doctype": "DefaultValue",
  "modified": "2024-07-10 10:24:35.790720",
  "name": "pi3l7a4gp3",
  "parent": "__default",
  "parentfield": "system_defaults",
  "parenttype": "__default"
 },
 {
  "defkey": "backup_limit",
  "defvalue": "3",
  "docstatus": 0,
  "doctype": "DefaultValue",
  "modified": "2024-07-10 10:24:35.791623",
  "name": "pi3l3gl2aq",
  "parent": "__default",
  "parentfield": "system_defaults",
  "parenttype": "__default"
 },
 {
  "defkey": "encrypt_backup",
  "defvalue": "0",
  "docstatus": 0,
  "doctype": "DefaultValue",
  "modified": "2024-07-10 10:24:35.792457",
  "name": "pi3lkcfeg1",
  "parent": "__default",
  "parentfield": "system_defaults",
  "parenttype": "__default"
 },
 {
  "defkey": "max_auto_email_report_per_user",
  "defvalue": "20",
  "docstatus": 0,
  "doctype": "DefaultValue",
  "modified": "2024-07-10 10:24:35.793322",
  "name": "pi3lnq5u36",
  "parent": "__default",
  "parentfield": "system_defaults",
  "parenttype": "__default"
 },
 {
  "defkey": "enable_scheduler",
  "defvalue": "0",
  "docstatus": 0,
  "doctype": "DefaultValue",
  "modified": "2024-07-10 10:24:35.794381",
  "name": "pi3ldtjoma",
  "parent": "__default",
  "parentfield": "system_defaults",
  "parenttype": "__default"
 },
 {
  "defkey": "dormant_days",
  "defvalue": "4",
  "docstatus": 0,
  "doctype": "DefaultValue",
  "modified": "2024-07-10 10:24:35.795198",
  "name": "pi3lt82jk5",
  "parent": "__default",
  "parentfield": "system_defaults",
  "parenttype": "__default"
 },
 {
  "defkey": "allow_error_traceback",
  "defvalue": "1",
  "docstatus": 0,
  "doctype": "DefaultValue",
  "modified": "2024-07-10 10:24:35.796014",
  "name": "pi3lpj0a9l",
  "parent": "__default",
  "parentfield": "system_defaults",
  "parenttype": "__default"
 },
 {
  "defkey": "link_field_results_limit",
  "defvalue": "10",
  "docstatus": 0,
  "doctype": "DefaultValue",
  "modified": "2024-07-10 10:24:35.797660",
  "name": "pi3l60vqev",
  "parent": "__default",
  "parentfield": "system_defaults",
  "parenttype": "__default"
 },
 {
  "defkey": "time_zone",
  "defvalue": "Asia/Kolkata",
  "docstatus": 0,
  "doctype": "DefaultValue",
  "modified": "2024-07-10 10:24:37.021242",
  "name": "pi42j0bd6b",
  "parent": "Guest",
  "parentfield": "system_defaults",
  "parenttype": "__default"
 },
 {
  "defkey": "add_taxes_from_item_tax_template",
  "defvalue": "1",
  "docstatus": 0,
  "doctype": "DefaultValue",
  "modified": "2024-07-10 10:26:19.283196",
  "name": "pj40js072o",
  "parent": "__default",
  "parentfield": "system_defaults",
  "parenttype": "__default"
 },
 {
  "defkey": "enable_common_party_accounting",
  "defvalue": "0",
  "docstatus": 0,
  "doctype": "DefaultValue",
  "modified": "2024-07-10 10:26:19.284497",
  "name": "pj40a1q9pg",
  "parent": "__default",
  "parentfield": "system_defaults",
  "parenttype": "__default"
 },
 {
  "defkey": "time_zone",
  "defvalue": "Asia/Kolkata",
  "docstatus": 0,
  "doctype": "DefaultValue",
  "modified": "2024-07-10 10:26:20.077263",
  "name": "pj489bn579",
  "parent": "Administrator",
  "parentfield": "system_defaults",
  "parenttype": "__default"
 },
 {
  "defkey": "installed_apps",
  "defvalue": "[\"frappe\", \"erpnext\", \"hrms\", \"xscore_management\"]",
  "docstatus": 0,
  "doctype": "DefaultValue",
  "modified": "2024-07-10 11:23:39.557424",
  "name": "rns33mvtoh",
  "parent": "__global",
  "parentfield": "system_defaults",
  "parenttype": "__default"
 },
 {
  "defkey": "email_user_password",
  "defvalue": "",
  "docstatus": 0,
  "doctype": "DefaultValue",
  "modified": "2024-07-11 07:25:39.063298",
  "name": "ho5e720vm7",
  "parent": "__default",
  "parentfield": "system_defaults",
  "parenttype": "__default"
 },
 {
  "defkey": "time_zone",
  "defvalue": "Asia/Kabul",
  "docstatus": 0,
  "doctype": "DefaultValue",
  "modified": "2024-07-11 07:25:39.392745",
  "name": "ho5hrlqpvi",
  "parent": "nam@gmail.com",
  "parentfield": "system_defaults",
  "parenttype": "__default"
 }
]